<?xml version="1.0" encoding="ISO-8859-1"?>
<root>
	<item id="Title"><![CDATA[Discuz! Plugin]]></item>
	<item id="Version"><![CDATA[X3.2]]></item>
	<item id="Time"><![CDATA[2016-05-31 19:01]]></item>
	<item id="From"><![CDATA[Discuz! Board (http://bbs.wuwenfu.net/)]]></item>
	<item id="Data">
		<item id="plugin">
			<item id="available"><![CDATA[0]]></item>
			<item id="adminid"><![CDATA[1]]></item>
			<item id="name"><![CDATA[北岸QQ登录]]></item>
			<item id="identifier"><![CDATA[htt_qqlogin]]></item>
			<item id="description"><![CDATA[通过QQ快速登录论坛]]></item>
			<item id="datatables"><![CDATA[]]></item>
			<item id="directory"><![CDATA[htt_qqlogin/]]></item>
			<item id="copyright"><![CDATA[吴文付]]></item>
			<item id="version"><![CDATA[1.3]]></item>
			<item id="__modules">
				<item id="0">
					<item id="name"><![CDATA[httqqlogin]]></item>
					<item id="param"><![CDATA[]]></item>
					<item id="menu"><![CDATA[]]></item>
					<item id="url"><![CDATA[]]></item>
					<item id="type"><![CDATA[11]]></item>
					<item id="adminid"><![CDATA[0]]></item>
					<item id="displayorder"><![CDATA[0]]></item>
					<item id="navtitle"><![CDATA[]]></item>
					<item id="navicon"><![CDATA[]]></item>
					<item id="navsubname"><![CDATA[]]></item>
					<item id="navsuburl"><![CDATA[]]></item>
				</item>
				<item id="1">
					<item id="name"><![CDATA[mobilehttqqlogin]]></item>
					<item id="param"><![CDATA[]]></item>
					<item id="menu"><![CDATA[]]></item>
					<item id="url"><![CDATA[]]></item>
					<item id="type"><![CDATA[28]]></item>
					<item id="adminid"><![CDATA[0]]></item>
					<item id="displayorder"><![CDATA[1]]></item>
					<item id="navtitle"><![CDATA[]]></item>
					<item id="navicon"><![CDATA[]]></item>
					<item id="navsubname"><![CDATA[]]></item>
					<item id="navsuburl"><![CDATA[]]></item>
				</item>
			</item>
		</item>
		<item id="version"><![CDATA[X3.2]]></item>
		<item id="var">
			<item id="0">
				<item id="displayorder"><![CDATA[0]]></item>
				<item id="title"><![CDATA[开关]]></item>
				<item id="description"><![CDATA[默认关闭]]></item>
				<item id="variable"><![CDATA[is_open]]></item>
				<item id="type"><![CDATA[select]]></item>
				<item id="value"><![CDATA[2]]></item>
				<item id="extra"><![CDATA[1=开启
2=关闭]]></item>
			</item>
			<item id="1">
				<item id="displayorder"><![CDATA[1]]></item>
				<item id="title"><![CDATA[APPID]]></item>
				<item id="description"><![CDATA[http://connect.qq.com/intro/login 申请appid]]></item>
				<item id="variable"><![CDATA[appid]]></item>
				<item id="type"><![CDATA[text]]></item>
				<item id="value"><![CDATA[]]></item>
				<item id="extra"><![CDATA[]]></item>
			</item>
			<item id="2">
				<item id="displayorder"><![CDATA[2]]></item>
				<item id="title"><![CDATA[KEY]]></item>
				<item id="description"><![CDATA[http://connect.qq.com/intro/login 申请key]]></item>
				<item id="variable"><![CDATA[key]]></item>
				<item id="type"><![CDATA[text]]></item>
				<item id="value"><![CDATA[]]></item>
				<item id="extra"><![CDATA[]]></item>
			</item>
			
			<item id="3">
				<item id="displayorder"><![CDATA[3]]></item>
				<item id="title"><![CDATA[用户名后缀]]></item>
				<item id="description"><![CDATA[默认后缀是字母或者数字混合。例如北岸的云_rq123]]></item>
				<item id="variable"><![CDATA[suffix]]></item>
				<item id="type"><![CDATA[select]]></item>
				<item id="value"><![CDATA[3]]></item>
				<item id="extra"><![CDATA[1=纯字母
2=纯数字
3=不限制]]></item>
			</item>
			
		</item>
		
		 <item id="language">
		<item id="templatelang">
			<item id='qq_tip1'>只需要一步，快速开始
			</item>
			<item id='qq_tip2'>其他登录
			</item>
			<item id='qq_tip3'>QQ登录
			</item>
		</item>
		
		</item>
		
		<item id="installfile"><![CDATA[install.php]]></item>
            <item id="uninstallfile"><![CDATA[uninstall.php]]></item>
	</item>
</root>